custom_app/__init__.py
custom_app/cli.py
custom_app/main.py
custom_app_lou-0.1.1.dist-info/licenses/LICENSE
custom_app_lou-0.1.1.dist-info/METADATA
custom_app_lou-0.1.1.dist-info/WHEEL
custom_app_lou-0.1.1.dist-info/entry_points.txt
custom_app_lou-0.1.1.dist-info/top_level.txt
custom_app_lou-0.1.1.dist-info/RECORD
