Metadata-Version: 2.4
Name: custom-app-Lou
Version: 0.1.1
Summary: Générateur de structure d'app Django personnalisée
Author: Lou christelle
Author-email: christellelou4@gmail.com
License: MIT
Classifier: Programming Language :: Python :: 3
Classifier: Framework :: Django
Classifier: License :: OSI Approved :: MIT License
License-File: LICENSE
Dynamic: author
Dynamic: author-email
Dynamic: classifier
Dynamic: description
Dynamic: description-content-type
Dynamic: license
Dynamic: license-file
Dynamic: summary
